<?xml version='1.1' encoding='UTF-8'?>
<fingerprint>
  <timestamp>2019-12-26 09:32:47.775 UTC</timestamp>
  <original>
    <name>Deploy_on_Docker_svr/com.example.maven-project:server</name>
    <number>4</number>
  </original>
  <md5sum>5d6e5de8afdb012d594eb22e40834c4e</md5sum>
  <fileName>com.example.maven-project:server.jar</fileName>
  <usages>
    <entry>
      <string>Deploy_on_Docker_svr/com.example.maven-project:server</string>
      <ranges>4</ranges>
    </entry>
    <entry>
      <string>Deploy_on_Docker_svr</string>
      <ranges>4</ranges>
    </entry>
  </usages>
  <facets/>
</fingerprint>